simple_dnf/__main__.py
simple_dnf/backend.py
simple_dnf/gtkapp.py
simple_dnf/locales/fr/LC_MESSAGES/simple_dnf.mo
simple_dnf/locales/fr/LC_MESSAGES/simple_dnf.po
simple_dnf/ui-classic.glade
simple_dnf/ui.glade
simple_dnf-0.1.1.dist-info/entry_points.txt
simple_dnf-0.1.1.dist-info/LICENSE
simple_dnf-0.1.1.dist-info/WHEEL
simple_dnf-0.1.1.dist-info/METADATA
simple_dnf-0.1.1.dist-info/RECORD
